walledai/__init__.py
walledai/constants.py
walledai/walledprotect.py
walledai/walledredact.py
walledai/custom_types/__init__.py
walledai/custom_types/guardrail.py
walledai/custom_types/pii.py
walledai-4.9.3.dist-info/licenses/LICENSE
walledai-4.9.3.dist-info/METADATA
walledai-4.9.3.dist-info/WHEEL
walledai-4.9.3.dist-info/top_level.txt
walledai-4.9.3.dist-info/RECORD
