Metadata-Version: 2.4
Name: walledai
Version: 4.9.3
Summary: A Python SDK for interacting with Walled AI
Author-email: Walled AI <rishabh@walled.ai>
License: MIT License
Requires-Python: >=3.8
License-File: LICENSE
Requires-Dist: aiohttp>=3.8.0
Requires-Dist: typing_extensions>=4.0.0
Requires-Dist: pandas>=1.3.0
Requires-Dist: scikit-learn>=1.0.0
Dynamic: license-file
